README.rst
setup.py
arxivpy/__init__.py
arxivpy/client.py
arxivpy/request.py
arxivpy/search.py
arxivpy.egg-info/PKG-INFO
arxivpy.egg-info/SOURCES.txt
arxivpy.egg-info/dependency_links.txt
arxivpy.egg-info/requires.txt
arxivpy.egg-info/top_level.txt
arxivpy.egg-info/zip-safe
arxivpy/exceptions/__init__.py
arxivpy/exceptions/empty_query_exception.py
arxivpy/exceptions/empty_term_exception.py
arxivpy/exceptions/unsuccessful_response_exception.py