Metadata-Version: 1.1
Name: arxivpy
Version: 0.0.2
Summary: Finds (and downloads) all journals from arXiv by given search criteria.
Home-page: https://github.com/monzita/arXivpy
Author: Monika Ilieva
Author-email: hidden@hidden.com
License: MIT
Keywords: arXiv science beautifulsoup search
Platform: UNKNOWN
Classifier: Development Status :: 3 - Alpha
Classifier: Intended Audience :: Education
Classifier: License :: OSI Approved :: MIT License
Classifier: Programming Language :: Python :: 3.5
Classifier: Programming Language :: Python :: 3.6
Classifier: Programming Language :: Python :: 3.7
Classifier: Programming Language :: Python :: 3 :: Only
Classifier: Topic :: Utilities
